<Product VersionDateTime="2019-10-07T07:48:24Z" UpdateType="Delete">
  <Identity>
    <TargetMarkets>
      <TargetMarket Code="GB"/>
      <TargetMarket Code="IE"/>
    </TargetMarkets>
    <ProductCodes>
      <Code Scheme="GTIN">5010292956843</Code>
      <Code Scheme="BRANDBANK:PVID">7301232</Code>
    </ProductCodes>
    <Subscription Id="42341" Code="AWIN002">Winterbotham Darby And Co Ltd</Subscription>
    <DiagnosticDescription Code="en-GB">Sun Soaked Spanish Omelette 300g</DiagnosticDescription>
    <Compliance>
      <EU1169_2011>SupplierStatedCompliant</EU1169_2011>
    </Compliance>
  </Identity>
</Product>